MANIFEST.in
README.rst
setup.py
opps_piston.egg-info/PKG-INFO
opps_piston.egg-info/SOURCES.txt
opps_piston.egg-info/dependency_links.txt
opps_piston.egg-info/namespace_packages.txt
opps_piston.egg-info/not-zip-safe
opps_piston.egg-info/top_level.txt
piston/__init__.py
piston/admin.py
piston/authentication.py
piston/decorator.py
piston/doc.py
piston/emitters.py
piston/forms.py
piston/handler.py
piston/handlers_doc.py
piston/managers.py
piston/middleware.py
piston/models.py
piston/oauth.py
piston/resource.py
piston/signals.py
piston/store.py
piston/test.py
piston/tests.py
piston/utils.py
piston/validate_jsonp.py
piston/templates/documentation.html
piston/templates/piston/authorize_token.html