Metadata-Version: 1.1
Name: opps-piston
Version: 0.2.4
Summary: Piston is a Opps (Django) mini-framework creating APIs.
Home-page: http://bitbucket.org/jespern/django-piston/wiki/Home
Author: Jesper Noehr
Author-email: jesper@noehr.org
License: BSD
Platform: UNKNOWN
Classifier: Development Status :: 3 - Alpha
Classifier: Framework :: Django
Classifier: Intended Audience :: Developers
Classifier: License :: OSI Approved :: BSD License
Classifier: Operating System :: OS Independent
Classifier: Programming Language :: Python
Classifier: Topic :: Internet :: WWW/HTTP
